mitstream/__init__.py
mitstream/mxs.py
mitstream-0.0.14.dist-info/METADATA
mitstream-0.0.14.dist-info/WHEEL
mitstream-0.0.14.dist-info/top_level.txt
mitstream-0.0.14.dist-info/RECORD
