Metadata-Version: 2.1
Name: mitstream
Version: 0.0.14
Summary: Support Functions for Modelling Trasnport
Home-page: UNKNOWN
Author: Mahmoud Ishtaiwi
Author-email: <m.ishtaiwe@gmail.com>
License: UNKNOWN
Keywords: python
Platform: UNKNOWN
Classifier: Development Status :: 1 - Planning
Classifier: Intended Audience :: Developers
Classifier: Programming Language :: Python :: 3
Classifier: Operating System :: Unix
Classifier: Operating System :: MacOS :: MacOS X
Classifier: Operating System :: Microsoft :: Windows
Requires-Dist: pandas
